tools/__init__.py
tools/speedtest.py
tools/spintax.py
nikebotandroid-0.0.1.dist-info/LICENSE
nikebotandroid-0.0.1.dist-info/METADATA
nikebotandroid-0.0.1.dist-info/WHEEL
nikebotandroid-0.0.1.dist-info/top_level.txt
nikebotandroid-0.0.1.dist-info/RECORD
