Metadata-Version: 2.1
Name: nikebotandroid
Version: 0.0.1
Summary: A retail automation bot for the mobile Nike app
Home-page: https://github.com/olegaobini/nikebot
Author: olega obini
Author-email: author@example.com
License: UNKNOWN
Project-URL: Bug Tracker, https://github.com/olegaobini/nikebot/issues
Platform: UNKNOWN
Classifier: Programming Language :: Python :: 3
Classifier: License :: OSI Approved :: MIT License
Classifier: Operating System :: OS Independent
Requires-Python: >=3.6
License-File: LICENSE
